eml_rename/__init__.py
eml_rename/core.py
eml_rename/locale/eml_rename.pot
eml_rename/locale/en/LC_MESSAGES/eml_rename.mo
eml_rename/locale/en.po
eml_rename/locale/es/LC_MESSAGES/eml_rename.mo
eml_rename/locale/es.po
eml_rename-0.3.0.dist-info/LICENSE
eml_rename-0.3.0.dist-info/METADATA
eml_rename-0.3.0.dist-info/WHEEL
eml_rename-0.3.0.dist-info/entry_points.txt
eml_rename-0.3.0.dist-info/RECORD
