Metadata-Version: 2.1
Name: eml-rename
Version: 0.3.0
Summary: Script renames all eml files in a directory using mail metadata
License: GPL-3.0 license
Author: turulomio
Author-email: turulomio@yahoo.es
Requires-Python: >=3.10,<4.0
Classifier: License :: Other/Proprietary License
Classifier: Programming Language :: Python :: 3
Classifier: Programming Language :: Python :: 3.10
Classifier: Programming Language :: Python :: 3.11
Requires-Dist: chardet (>=5.1.0,<6.0.0)
Requires-Dist: colorama (>=0.4.6,<0.5.0)
Requires-Dist: tqdm (>=4.65.0,<5.0.0)
